compas_convert/__init__.py
compas_convert/_version.py
compas_convert/native.py
compas_convert/py.typed
compas_convert/install/__init__.py
compas_convert/install/rhino.py
compas_convert/rhino/__init__.py
compas_convert/rhino/compas_to_rhino.py
compas_convert/rhino/rhino_to_compas.py
compas_convert/rhino/grasshopper_components/__init__.py
compas_convert/rhino/grasshopper_components/Cc_Convert/code.py
compas_convert/rhino/grasshopper_components/Cc_Convert/icon.png
compas_convert/rhino/grasshopper_components/Cc_Convert/metadata.json
compas_convert/rhino/grasshopper_components/ghuser/Cc_Convert.ghuser
compas_convert/universal_converter/__init__.py
compas_convert/universal_converter/type_converter_match.py
compas_convert/universal_converter/universal_converter.py
compas_convert-0.1.4.dist-info/LICENSE
compas_convert-0.1.4.dist-info/METADATA
compas_convert-0.1.4.dist-info/WHEEL
compas_convert-0.1.4.dist-info/top_level.txt
compas_convert-0.1.4.dist-info/RECORD
