Metadata-Version: 2.1
Name: compas-convert
Version: 0.1.4
Summary: Conversions between compas objects and CAD specific objects.
Home-page: https://github.com/tetov/compas_convert
Author: Anton Tetov Johansson
Maintainer: Anton Tetov Johansson
Maintainer-email: anton@tetov.xyz
License: MIT license
Project-URL: Repository, https://github.com/tetov/compas_convert
Project-URL: Issues, https://github.com/tetov/compas_convert/issues
Keywords: geometry
Platform: UNKNOWN
Classifier: Development Status :: 4 - Beta
Classifier: Intended Audience :: Developers
Classifier: Topic :: Scientific/Engineering
Classifier: License :: OSI Approved :: MIT License
Classifier: Operating System :: Unix
Classifier: Operating System :: POSIX
Classifier: Operating System :: Microsoft :: Windows
Classifier: Programming Language :: Python
Classifier: Programming Language :: Python :: 3
Classifier: Programming Language :: Python :: 3.7
Classifier: Programming Language :: Python :: 3.8
Classifier: Programming Language :: Python :: 3.9
Classifier: Programming Language :: Python :: Implementation :: CPython
Classifier: Programming Language :: Python :: Implementation :: IronPython
Requires-Python: >=3.7
License-File: LICENSE
Requires-Dist: compas (<1.11,>=0.17.2)
Provides-Extra: dev
Requires-Dist: black (>=21.5b2) ; extra == 'dev'
Requires-Dist: build (>=0.4.0) ; extra == 'dev'
Requires-Dist: flake8 ; extra == 'dev'
Requires-Dist: graphviz (>=0.16) ; extra == 'dev'
Requires-Dist: invoke (>=1.5.0) ; extra == 'dev'
Requires-Dist: mypy (>=0.790) ; extra == 'dev'
Requires-Dist: pydocstyle[toml] ; extra == 'dev'
Requires-Dist: pytest (>=6) ; extra == 'dev'
Requires-Dist: reorder-python-imports (>=2.5.0) ; extra == 'dev'
Requires-Dist: setuptools-scm[toml] (<7.0,>=4.1) ; extra == 'dev'
Requires-Dist: importlib-metadata ; (python_version < "3.8") and extra == 'dev'
